fastapi_blog/__init__.py
fastapi_blog/helpers.py
fastapi_blog/main.py
fastapi_blog/router.py
fastapi_blog/static/custom.css
fastapi_blog/static/normalize.css
fastapi_blog/static/pygments.css
fastapi_blog/static/sakura.css
fastapi_blog/templates/404.html
fastapi_blog/templates/index.html
fastapi_blog/templates/page.html
fastapi_blog/templates/post.html
fastapi_blog/templates/posts.html
fastapi_blog/templates/tag.html
fastapi_blog/templates/tags.html
fastapi_blog/templates/layout/base.html
fastapi_blog/templates/partials/_post_short.html
fastapi_blog-0.6.0.dist-info/LICENSE.md
fastapi_blog-0.6.0.dist-info/METADATA
fastapi_blog-0.6.0.dist-info/WHEEL
fastapi_blog-0.6.0.dist-info/top_level.txt
fastapi_blog-0.6.0.dist-info/RECORD
