Metadata-Version: 2.1
Name: fastapi-blog
Version: 0.6.0
Summary: Blogging for FastAPI
Author-email: Daniel Roy Greenfeld <daniel@feldroy.com>
Maintainer-email: Daniel Roy Greenfeld <daniel@feldroy.com>
License: FSL-1.0-Apache-2.0
Project-URL: bugs, https://github.com/pydanny/fastapi-blog/issues
Project-URL: changelog, https://github.com/pydanny/fastapi-blog/blob/master/changelog.md
Project-URL: homepage, https://github.com/pydanny/fastapi-blog
Classifier: Development Status :: 2 - Pre-Alpha
Classifier: Environment :: Web Environment
Classifier: Framework :: FastAPI
Classifier: License :: Other/Proprietary License
Classifier: Programming Language :: Python :: 3.12
Classifier: Topic :: Text Processing :: Markup :: Markdown
Requires-Python: >=3.10
License-File: LICENSE.md
Requires-Dist: fastapi >=0.109.2
Requires-Dist: jinja2 >=3.1.3
Requires-Dist: jinja2-time >=0.2.0
Requires-Dist: markdown >=3.5.2
Requires-Dist: pyyaml >=6.0.1
Requires-Dist: pymdown-extensions >=10.7
Requires-Dist: uvicorn >=0.27.1
Provides-Extra: dev
Requires-Dist: httpx ; extra == 'dev'
Requires-Dist: ruff ==0.2.2 ; extra == 'dev'
Requires-Dist: pytest ==8.0.1 ; extra == 'dev'
Requires-Dist: coverage ==7.4.1 ; extra == 'dev'
Requires-Dist: mypy ==1.8.0 ; extra == 'dev'
Requires-Dist: types-Markdown ==3.5.0.20240129 ; extra == 'dev'
Requires-Dist: types-PyYAML ==6.0.12.12 ; extra == 'dev'
